{
    "description": "TYPE: CUSTOM\nMaterial Theme Builder export 2026-06-08 07:45:58",
    "seed": "#00A1BC",
    "coreColors": {
        "primary": "#00A1BC"
    },
    "extendedColors": [],
    "schemes": {
        "light": {
            "primary": "#00687A",
            "surfaceTint": "#00687A",
            "onPrimary": "#FFFFFF",
            "primaryContainer": "#ACEDFF",
            "onPrimaryContainer": "#004E5C",
            "secondary": "#4B6269",
            "onSecondary": "#FFFFFF",
            "secondaryContainer": "#CEE7EF",
            "onSecondaryContainer": "#334A51",
            "tertiary": "#565D7E",
            "onTertiary": "#FFFFFF",
            "tertiaryContainer": "#DDE1FF",
            "onTertiaryContainer": "#3F4565",
            "error": "#BA1A1A",
            "onError": "#FFFFFF",
            "errorContainer": "#FFDAD6",
            "onErrorContainer": "#93000A",
            "background": "#F5FAFC",
            "onBackground": "#171C1E",
            "surface": "#F5FAFC",
            "onSurface": "#171C1E",
            "surfaceVariant": "#DBE4E7",
            "onSurfaceVariant": "#3F484B",
            "outline": "#70797B",
            "outlineVariant": "#BFC8CB",
            "shadow": "#000000",
            "scrim": "#000000",
            "inverseSurface": "#2C3133",
            "inverseOnSurface": "#ECF2F4",
            "inversePrimary": "#84D2E7",
            "primaryFixed": "#ACEDFF",
            "onPrimaryFixed": "#001F26",
            "primaryFixedDim": "#84D2E7",
            "onPrimaryFixedVariant": "#004E5C",
            "secondaryFixed": "#CEE7EF",
            "onSecondaryFixed": "#061F24",
            "secondaryFixedDim": "#B2CBD2",
            "onSecondaryFixedVariant": "#334A51",
            "tertiaryFixed": "#DDE1FF",
            "onTertiaryFixed": "#131937",
            "tertiaryFixedDim": "#BFC4EB",
            "onTertiaryFixedVariant": "#3F4565",
            "surfaceDim": "#D5DBDD",
            "surfaceBright": "#F5FAFC",
            "surfaceContainerLowest": "#FFFFFF",
            "surfaceContainerLow": "#EFF4F7",
            "surfaceContainer": "#E9EFF1",
            "surfaceContainerHigh": "#E4E9EB",
            "surfaceContainerHighest": "#DEE3E5"
        },
        "light-medium-contrast": {
            "primary": "#003C47",
            "surfaceTint": "#00687A",
            "onPrimary": "#FFFFFF",
            "primaryContainer": "#1E778A",
            "onPrimaryContainer": "#FFFFFF",
            "secondary": "#233A40",
            "onSecondary": "#FFFFFF",
            "secondaryContainer": "#597178",
            "onSecondaryContainer": "#FFFFFF",
            "tertiary": "#2E3453",
            "onTertiary": "#FFFFFF",
            "tertiaryContainer": "#656B8D",
            "onTertiaryContainer": "#FFFFFF",
            "error": "#740006",
            "onError": "#FFFFFF",
            "errorContainer": "#CF2C27",
            "onErrorContainer": "#FFFFFF",
            "background": "#F5FAFC",
            "onBackground": "#171C1E",
            "surface": "#F5FAFC",
            "onSurface": "#0C1214",
            "surfaceVariant": "#DBE4E7",
            "onSurfaceVariant": "#2F383A",
            "outline": "#4B5457",
            "outlineVariant": "#666F71",
            "shadow": "#000000",
            "scrim": "#000000",
            "inverseSurface": "#2C3133",
            "inverseOnSurface": "#ECF2F4",
            "inversePrimary": "#84D2E7",
            "primaryFixed": "#1E778A",
            "onPrimaryFixed": "#FFFFFF",
            "primaryFixedDim": "#005D6E",
            "onPrimaryFixedVariant": "#FFFFFF",
            "secondaryFixed": "#597178",
            "onSecondaryFixed": "#FFFFFF",
            "secondaryFixedDim": "#41585F",
            "onSecondaryFixedVariant": "#FFFFFF",
            "tertiaryFixed": "#656B8D",
            "onTertiaryFixed": "#FFFFFF",
            "tertiaryFixedDim": "#4D5374",
            "onTertiaryFixedVariant": "#FFFFFF",
            "surfaceDim": "#C2C7C9",
            "surfaceBright": "#F5FAFC",
            "surfaceContainerLowest": "#FFFFFF",
            "surfaceContainerLow": "#EFF4F7",
            "surfaceContainer": "#E4E9EB",
            "surfaceContainerHigh": "#D8DEE0",
            "surfaceContainerHighest": "#CDD2D5"
        },
        "light-high-contrast": {
            "primary": "#00313B",
            "surfaceTint": "#00687A",
            "onPrimary": "#FFFFFF",
            "primaryContainer": "#00515F",
            "onPrimaryContainer": "#FFFFFF",
            "secondary": "#182F35",
            "onSecondary": "#FFFFFF",
            "secondaryContainer": "#364D53",
            "onSecondaryContainer": "#FFFFFF",
            "tertiary": "#242A48",
            "onTertiary": "#FFFFFF",
            "tertiaryContainer": "#414767",
            "onTertiaryContainer": "#FFFFFF",
            "error": "#600004",
            "onError": "#FFFFFF",
            "errorContainer": "#98000A",
            "onErrorContainer": "#FFFFFF",
            "background": "#F5FAFC",
            "onBackground": "#171C1E",
            "surface": "#F5FAFC",
            "onSurface": "#000000",
            "surfaceVariant": "#DBE4E7",
            "onSurfaceVariant": "#000000",
            "outline": "#252E30",
            "outlineVariant": "#424B4D",
            "shadow": "#000000",
            "scrim": "#000000",
            "inverseSurface": "#2C3133",
            "inverseOnSurface": "#FFFFFF",
            "inversePrimary": "#84D2E7",
            "primaryFixed": "#00515F",
            "onPrimaryFixed": "#FFFFFF",
            "primaryFixedDim": "#003843",
            "onPrimaryFixedVariant": "#FFFFFF",
            "secondaryFixed": "#364D53",
            "onSecondaryFixed": "#FFFFFF",
            "secondaryFixedDim": "#1F363C",
            "onSecondaryFixedVariant": "#FFFFFF",
            "tertiaryFixed": "#414767",
            "onTertiaryFixed": "#FFFFFF",
            "tertiaryFixedDim": "#2B314F",
            "onTertiaryFixedVariant": "#FFFFFF",
            "surfaceDim": "#B4BABC",
            "surfaceBright": "#F5FAFC",
            "surfaceContainerLowest": "#FFFFFF",
            "surfaceContainerLow": "#ECF2F4",
            "surfaceContainer": "#DEE3E5",
            "surfaceContainerHigh": "#D0D5D7",
            "surfaceContainerHighest": "#C2C7C9"
        },
        "dark": {
            "primary": "#84D2E7",
            "surfaceTint": "#84D2E7",
            "onPrimary": "#003640",
            "primaryContainer": "#004E5C",
            "onPrimaryContainer": "#ACEDFF",
            "secondary": "#B2CBD2",
            "onSecondary": "#1D343A",
            "secondaryContainer": "#334A51",
            "onSecondaryContainer": "#CEE7EF",
            "tertiary": "#BFC4EB",
            "onTertiary": "#282F4D",
            "tertiaryContainer": "#3F4565",
            "onTertiaryContainer": "#DDE1FF",
            "error": "#FFB4AB",
            "onError": "#690005",
            "errorContainer": "#93000A",
            "onErrorContainer": "#FFDAD6",
            "background": "#0F1416",
            "onBackground": "#DEE3E5",
            "surface": "#0F1416",
            "onSurface": "#DEE3E5",
            "surfaceVariant": "#3F484B",
            "onSurfaceVariant": "#BFC8CB",
            "outline": "#899295",
            "outlineVariant": "#3F484B",
            "shadow": "#000000",
            "scrim": "#000000",
            "inverseSurface": "#DEE3E5",
            "inverseOnSurface": "#2C3133",
            "inversePrimary": "#00687A",
            "primaryFixed": "#ACEDFF",
            "onPrimaryFixed": "#001F26",
            "primaryFixedDim": "#84D2E7",
            "onPrimaryFixedVariant": "#004E5C",
            "secondaryFixed": "#CEE7EF",
            "onSecondaryFixed": "#061F24",
            "secondaryFixedDim": "#B2CBD2",
            "onSecondaryFixedVariant": "#334A51",
            "tertiaryFixed": "#DDE1FF",
            "onTertiaryFixed": "#131937",
            "tertiaryFixedDim": "#BFC4EB",
            "onTertiaryFixedVariant": "#3F4565",
            "surfaceDim": "#0F1416",
            "surfaceBright": "#343A3C",
            "surfaceContainerLowest": "#090F11",
            "surfaceContainerLow": "#171C1E",
            "surfaceContainer": "#1B2022",
            "surfaceContainerHigh": "#252B2D",
            "surfaceContainerHighest": "#303638"
        },
        "dark-medium-contrast": {
            "primary": "#9AE8FD",
            "surfaceTint": "#84D2E7",
            "onPrimary": "#002A33",
            "primaryContainer": "#4C9BAF",
            "onPrimaryContainer": "#000000",
            "secondary": "#C8E1E8",
            "onSecondary": "#11292F",
            "secondaryContainer": "#7D959C",
            "onSecondaryContainer": "#000000",
            "tertiary": "#D5DAFF",
            "onTertiary": "#1D2442",
            "tertiaryContainer": "#898FB3",
            "onTertiaryContainer": "#000000",
            "error": "#FFD2CC",
            "onError": "#540003",
            "errorContainer": "#FF5449",
            "onErrorContainer": "#000000",
            "background": "#0F1416",
            "onBackground": "#DEE3E5",
            "surface": "#0F1416",
            "onSurface": "#FFFFFF",
            "surfaceVariant": "#3F484B",
            "onSurfaceVariant": "#D5DEE1",
            "outline": "#AAB3B6",
            "outlineVariant": "#899295",
            "shadow": "#000000",
            "scrim": "#000000",
            "inverseSurface": "#DEE3E5",
            "inverseOnSurface": "#252B2D",
            "inversePrimary": "#004F5E",
            "primaryFixed": "#ACEDFF",
            "onPrimaryFixed": "#001419",
            "primaryFixedDim": "#84D2E7",
            "onPrimaryFixedVariant": "#003C47",
            "secondaryFixed": "#CEE7EF",
            "onSecondaryFixed": "#001419",
            "secondaryFixedDim": "#B2CBD2",
            "onSecondaryFixedVariant": "#233A40",
            "tertiaryFixed": "#DDE1FF",
            "onTertiaryFixed": "#080F2C",
            "tertiaryFixedDim": "#BFC4EB",
            "onTertiaryFixedVariant": "#2E3453",
            "surfaceDim": "#0F1416",
            "surfaceBright": "#404547",
            "surfaceContainerLowest": "#04080A",
            "surfaceContainerLow": "#191E20",
            "surfaceContainer": "#23292B",
            "surfaceContainerHigh": "#2E3335",
            "surfaceContainerHighest": "#393F40"
        },
        "dark-high-contrast": {
            "primary": "#D6F5FF",
            "surfaceTint": "#84D2E7",
            "onPrimary": "#000000",
            "primaryContainer": "#80CEE3",
            "onPrimaryContainer": "#000D12",
            "secondary": "#DBF4FC",
            "onSecondary": "#000000",
            "secondaryContainer": "#AEC7CE",
            "onSecondaryContainer": "#000D12",
            "tertiary": "#EFEFFF",
            "onTertiary": "#000000",
            "tertiaryContainer": "#BBC1E7",
            "onTertiaryContainer": "#030826",
            "error": "#FFECE9",
            "onError": "#000000",
            "errorContainer": "#FFAEA4",
            "onErrorContainer": "#220001",
            "background": "#0F1416",
            "onBackground": "#DEE3E5",
            "surface": "#0F1416",
            "onSurface": "#FFFFFF",
            "surfaceVariant": "#3F484B",
            "onSurfaceVariant": "#FFFFFF",
            "outline": "#E9F1F5",
            "outlineVariant": "#BBC4C7",
            "shadow": "#000000",
            "scrim": "#000000",
            "inverseSurface": "#DEE3E5",
            "inverseOnSurface": "#000000",
            "inversePrimary": "#004F5E",
            "primaryFixed": "#ACEDFF",
            "onPrimaryFixed": "#000000",
            "primaryFixedDim": "#84D2E7",
            "onPrimaryFixedVariant": "#001419",
            "secondaryFixed": "#CEE7EF",
            "onSecondaryFixed": "#000000",
            "secondaryFixedDim": "#B2CBD2",
            "onSecondaryFixedVariant": "#001419",
            "tertiaryFixed": "#DDE1FF",
            "onTertiaryFixed": "#000000",
            "tertiaryFixedDim": "#BFC4EB",
            "onTertiaryFixedVariant": "#080F2C",
            "surfaceDim": "#0F1416",
            "surfaceBright": "#4B5153",
            "surfaceContainerLowest": "#000000",
            "surfaceContainerLow": "#1B2022",
            "surfaceContainer": "#2C3133",
            "surfaceContainerHigh": "#373C3E",
            "surfaceContainerHighest": "#42484A"
        }
    },
    "palettes": {
        "primary": {
            "0": "#000000",
            "5": "#001419",
            "10": "#001F26",
            "15": "#002A33",
            "20": "#003640",
            "25": "#00424E",
            "30": "#004E5C",
            "35": "#005B6B",
            "40": "#00687A",
            "50": "#008399",
            "60": "#009EB9",
            "70": "#3BBAD5",
            "80": "#5ED6F2",
            "90": "#ACEDFF",
            "95": "#D8F6FF",
            "98": "#F0FBFF",
            "99": "#F8FDFF",
            "100": "#FFFFFF"
        },
        "secondary": {
            "0": "#000000",
            "5": "#001419",
            "10": "#071E24",
            "15": "#13292F",
            "20": "#1E3439",
            "25": "#293F45",
            "30": "#344A50",
            "35": "#40565C",
            "40": "#4C6268",
            "50": "#647B81",
            "60": "#7E949B",
            "70": "#98AFB6",
            "80": "#B3CAD2",
            "90": "#CFE7EE",
            "95": "#DDF5FC",
            "98": "#F0FBFF",
            "99": "#F8FDFF",
            "100": "#FFFFFF"
        },
        "tertiary": {
            "0": "#000000",
            "5": "#080F2A",
            "10": "#141A36",
            "15": "#1E2440",
            "20": "#292F4C",
            "25": "#343A57",
            "30": "#3F4563",
            "35": "#4B5170",
            "40": "#575D7C",
            "50": "#707596",
            "60": "#898FB1",
            "70": "#A4A9CD",
            "80": "#BFC4E9",
            "90": "#DDE1FF",
            "95": "#F0EFFF",
            "98": "#FBF8FF",
            "99": "#FEFBFF",
            "100": "#FFFFFF"
        },
        "neutral": {
            "0": "#000000",
            "5": "#0E1112",
            "10": "#191C1D",
            "15": "#232627",
            "20": "#2E3132",
            "25": "#393C3D",
            "30": "#444748",
            "35": "#505354",
            "40": "#5C5F60",
            "50": "#757778",
            "60": "#8F9192",
            "70": "#A9ABAC",
            "80": "#C5C7C8",
            "90": "#E1E3E4",
            "95": "#EFF1F2",
            "98": "#F8F9FA",
            "99": "#FBFCFD",
            "100": "#FFFFFF"
        },
        "neutral-variant": {
            "0": "#000000",
            "5": "#0A1214",
            "10": "#151D1F",
            "15": "#1F272A",
            "20": "#2A3234",
            "25": "#343D3F",
            "30": "#40484B",
            "35": "#4B5456",
            "40": "#576062",
            "50": "#70787B",
            "60": "#8A9295",
            "70": "#A4ADB0",
            "80": "#BFC8CB",
            "90": "#DBE4E7",
            "95": "#EAF2F5",
            "98": "#F2FBFE",
            "99": "#F8FDFF",
            "100": "#FFFFFF"
        }
    }
}